ws_utils/__init__.py
ws_utils/worksheet_iterator.py
worksheet_iterator-0.1.5.dist-info/METADATA
worksheet_iterator-0.1.5.dist-info/WHEEL
worksheet_iterator-0.1.5.dist-info/RECORD
