Metadata-Version: 2.4
Name: worksheet-iterator
Version: 0.1.5
Summary: A chainable worksheet iterator utility based on XlsxWriter.
Project-URL: Homepage, https://github.com/realkcn/worksheet-iterator
Author: realkcn
License: MIT
Requires-Python: >=3.9
Requires-Dist: xlsxwriter>=3.0.0
